argman/__init__.py
argman/argman.py
argman-0.4.0.dist-info/licenses/LICENSE
argman-0.4.0.dist-info/METADATA
argman-0.4.0.dist-info/WHEEL
argman-0.4.0.dist-info/top_level.txt
argman-0.4.0.dist-info/RECORD
