Metadata-Version: 2.4
Name: argman
Version: 0.4.0
Summary: A lightweight argument manager for Python CLI tools
Author-email: Seyed Mohammad Javad Taghipoor <smjavadt.1379@gmail.com>
License: LGPL-3.0-or-later
Project-URL: Homepage, https://github.com/smjt2000/argman
Keywords: cli,argparse,arguments,parser
Classifier: Programming Language :: Python :: 3
Classifier: License :: OSI Approved :: GNU Lesser General Public License v3 or later (LGPLv3+)
Classifier: Operating System :: OS Independent
Requires-Python: >=3.10
License-File: LICENSE
Dynamic: license-file
